licface/__init__.py
licface/__version__.py
licface/config.py
licface/custom_rich_help_formatter.py
licface/jsoncolor.py
licface/make_colors_help_formatter.py
licface/makelist.py
licface-0.35.2.dist-info/METADATA
licface-0.35.2.dist-info/WHEEL
licface-0.35.2.dist-info/top_level.txt
licface-0.35.2.dist-info/RECORD
