Metadata-Version: 2.4
Name: licface
Version: 0.35.2
Summary: my tools
Home-page: https://github.com/cumulus13/licface
Author: Hadi Cahyadi
Author-email: cumulus13@gmail.com
Project-URL: Bug Reports, https://github.com/cumulus13/licface/issues
Project-URL: Source, https://github.com/cumulus13/licface
Project-URL: Documentation, https://github.com/cumulus13/licface#readme
Keywords: licface tools
Classifier: Development Status :: 4 - Beta
Classifier: Intended Audience :: Developers
Classifier: License :: OSI Approved :: MIT License
Classifier: Operating System :: OS Independent
Classifier: Programming Language :: Python :: 3
Classifier: Programming Language :: Python :: 3.7
Classifier: Programming Language :: Python :: 3.8
Classifier: Programming Language :: Python :: 3.9
Classifier: Programming Language :: Python :: 3.10
Classifier: Programming Language :: Python :: 3.11
Classifier: Programming Language :: Python :: 3.12
Classifier: Topic :: Software Development :: Libraries :: Python Modules
Classifier: Topic :: System :: Logging
Classifier: Topic :: Utilities
Requires-Python: >=3.7
Requires-Dist: rich
Requires-Dist: rich_argparse
Requires-Dist: pydebugger
Requires-Dist: configset
Requires-Dist: pygments
Requires-Dist: json5
Requires-Dist: clipboard
Requires-Dist: make_colors
Provides-Extra: dev
Requires-Dist: pytest>=6.0; extra == "dev"
Requires-Dist: pytest-cov; extra == "dev"
Requires-Dist: black; extra == "dev"
Requires-Dist: flake8; extra == "dev"
Requires-Dist: mypy; extra == "dev"
Dynamic: author
Dynamic: author-email
Dynamic: classifier
Dynamic: description
Dynamic: description-content-type
Dynamic: home-page
Dynamic: keywords
Dynamic: project-url
Dynamic: provides-extra
Dynamic: requires-dist
Dynamic: requires-python
Dynamic: summary
